odoo/addons/sale_order_import_ubl/README.rst
odoo/addons/sale_order_import_ubl/__init__.py
odoo/addons/sale_order_import_ubl/__manifest__.py
odoo/addons/sale_order_import_ubl/demo/demo_data.xml
odoo/addons/sale_order_import_ubl/i18n/sale_order_import_ubl.pot
odoo/addons/sale_order_import_ubl/readme/CONTRIBUTORS.rst
odoo/addons/sale_order_import_ubl/readme/DESCRIPTION.rst
odoo/addons/sale_order_import_ubl/readme/USAGE.rst
odoo/addons/sale_order_import_ubl/static/description/icon.png
odoo/addons/sale_order_import_ubl/static/description/index.html
odoo/addons/sale_order_import_ubl/tests/__init__.py
odoo/addons/sale_order_import_ubl/tests/test_ubl_order_import.py
odoo/addons/sale_order_import_ubl/tests/files/UBL-Order-2.0-Example.xml
odoo/addons/sale_order_import_ubl/tests/files/UBL-Order-2.1-Example.xml
odoo/addons/sale_order_import_ubl/tests/files/UBL-RequestForQuotation-2.0-Example.xml
odoo/addons/sale_order_import_ubl/tests/files/UBL-RequestForQuotation-2.1-Example.xml
odoo/addons/sale_order_import_ubl/wizard/__init__.py
odoo/addons/sale_order_import_ubl/wizard/sale_order_import.py
odoo11_addon_sale_order_import_ubl-11.0.1.0.0.99.dev5.dist-info/METADATA
odoo11_addon_sale_order_import_ubl-11.0.1.0.0.99.dev5.dist-info/WHEEL
odoo11_addon_sale_order_import_ubl-11.0.1.0.0.99.dev5.dist-info/top_level.txt
odoo11_addon_sale_order_import_ubl-11.0.1.0.0.99.dev5.dist-info/RECORD
